tourism_platform_lib/__init__.py
tourism_platform_lib/place_search/__init__.py
tourism_platform_lib/place_search/tfidf_search.py
tourism_platform_lib/utils/__init__.py
tourism_platform_lib/utils/db_utils.py
tourism_platform_lib/utils/json_utils.py
tourism_platform_lib/utils/param_utils.py
gbdi_tourism_platform_lib-0.0.1.dist-info/METADATA
gbdi_tourism_platform_lib-0.0.1.dist-info/WHEEL
gbdi_tourism_platform_lib-0.0.1.dist-info/top_level.txt
gbdi_tourism_platform_lib-0.0.1.dist-info/RECORD
