Metadata-Version: 2.1
Name: gbdi-tourism-platform-lib
Version: 0.0.1
Summary: private python packages for tourism-platform
Home-page: UNKNOWN
Author: Nanont Noparat, Chainarong Tumapha
Author-email: nanont.no@depa.or.th, chainarong.tu@depa.or.th
License: UNKNOWN
Platform: UNKNOWN
Requires-Python: >=3.6
Requires-Dist: bson (==0.5.10)
Requires-Dist: pymongo (==3.11.1)
Requires-Dist: python-dateutil (==2.8.1)
Requires-Dist: six (==1.15.0)
Provides-Extra: full
Requires-Dist: certifi (==2020.11.8) ; extra == 'full'
Requires-Dist: chardet (==3.0.4) ; extra == 'full'
Requires-Dist: click (==7.1.2) ; extra == 'full'
Requires-Dist: idna (==2.10) ; extra == 'full'
Requires-Dist: joblib (==0.17.0) ; extra == 'full'
Requires-Dist: numpy (==1.19.4) ; extra == 'full'
Requires-Dist: pandas (==1.1.4) ; extra == 'full'
Requires-Dist: pythainlp (==2.2.5) ; extra == 'full'
Requires-Dist: python-crfsuite (==0.9.7) ; extra == 'full'
Requires-Dist: python-dateutil (==2.8.1) ; extra == 'full'
Requires-Dist: pytz (==2020.4) ; extra == 'full'
Requires-Dist: regex (==2020.11.13) ; extra == 'full'
Requires-Dist: requests (==2.25.0) ; extra == 'full'
Requires-Dist: scikit-learn (==0.23.2) ; extra == 'full'
Requires-Dist: scipy (==1.5.4) ; extra == 'full'
Requires-Dist: sklearn (==0.0) ; extra == 'full'
Requires-Dist: threadpoolctl (==2.1.0) ; extra == 'full'
Requires-Dist: tinydb (==4.3.0) ; extra == 'full'
Requires-Dist: tqdm (==4.54.0) ; extra == 'full'
Requires-Dist: urllib3 (==1.26.2) ; extra == 'full'
Provides-Extra: place_search
Requires-Dist: certifi (==2020.11.8) ; extra == 'place_search'
Requires-Dist: chardet (==3.0.4) ; extra == 'place_search'
Requires-Dist: click (==7.1.2) ; extra == 'place_search'
Requires-Dist: idna (==2.10) ; extra == 'place_search'
Requires-Dist: joblib (==0.17.0) ; extra == 'place_search'
Requires-Dist: numpy (==1.19.4) ; extra == 'place_search'
Requires-Dist: pandas (==1.1.4) ; extra == 'place_search'
Requires-Dist: pythainlp (==2.2.5) ; extra == 'place_search'
Requires-Dist: python-crfsuite (==0.9.7) ; extra == 'place_search'
Requires-Dist: python-dateutil (==2.8.1) ; extra == 'place_search'
Requires-Dist: pytz (==2020.4) ; extra == 'place_search'
Requires-Dist: regex (==2020.11.13) ; extra == 'place_search'
Requires-Dist: requests (==2.25.0) ; extra == 'place_search'
Requires-Dist: scikit-learn (==0.23.2) ; extra == 'place_search'
Requires-Dist: scipy (==1.5.4) ; extra == 'place_search'
Requires-Dist: sklearn (==0.0) ; extra == 'place_search'
Requires-Dist: threadpoolctl (==2.1.0) ; extra == 'place_search'
Requires-Dist: tinydb (==4.3.0) ; extra == 'place_search'
Requires-Dist: tqdm (==4.54.0) ; extra == 'place_search'
Requires-Dist: urllib3 (==1.26.2) ; extra == 'place_search'
Provides-Extra: recommender
